ta_formula/indicators.cpython-39-darwin.so
ta_formula/numpy_funcs.py
ta_formula/dataflow_misc.py
ta_formula/calculation.py
ta_formula/__init__.py
ta_formula/strategy.py
ta_formula/indicators.pxd
ta_formula/datasource.py
ta_formula/strategy_ast.py
ta_formula/dataflow_aio.py
ta_formula/exceptions.py
ta_formula/dataflow.py
ta_formula/_ta_lib.pxd
ta_formula/.dylibs/libta_lib.0.0.0.dylib
ta_formula-1.1.4.dist-info/RECORD
ta_formula-1.1.4.dist-info/LICENSE
ta_formula-1.1.4.dist-info/WHEEL
ta_formula-1.1.4.dist-info/entry_points.txt
ta_formula-1.1.4.dist-info/top_level.txt
ta_formula-1.1.4.dist-info/METADATA
