Metadata-Version: 2.2
Name: ta_formula
Version: 1.1.4
Summary: talib extension for formula computation
Author-email: sric0880 <justgotpaid88@qq.com>
License: MIT License
Project-URL: Repository, https://github.com/sric0880/ta_formula
Project-URL: Issues, https://github.com/sric0880/ta_formula/issues
Keywords: formula,quant,ta,TA-Lib,talib,ta-lib,technical-analysis,indicators,technical-indicators,quantum-computing
Classifier: Development Status :: 2 - Pre-Alpha
Classifier: Operating System :: Unix
Classifier: Operating System :: POSIX
Classifier: Operating System :: MacOS :: MacOS X
Classifier: Operating System :: Microsoft :: Windows
Classifier: Programming Language :: Python
Classifier: Programming Language :: Python :: 3.9
Classifier: Programming Language :: Cython
Classifier: Topic :: Office/Business :: Financial
Classifier: Topic :: Scientific/Engineering :: Mathematics
Classifier: Intended Audience :: Developers
Classifier: Intended Audience :: Science/Research
Classifier: Intended Audience :: Financial and Insurance Industry
Requires-Python: >=3.9
License-File: LICENSE
Requires-Dist: Cython>=3.0.10
